claude_wrapper/__init__.py
claude_wrapper/_version.py
claude_wrapper/api/__init__.py
claude_wrapper/api/models.py
claude_wrapper/api/server.py
claude_wrapper/cli/__init__.py
claude_wrapper/cli/main.py
claude_wrapper/core/__init__.py
claude_wrapper/core/client.py
claude_wrapper/core/exceptions.py
claude_wrapper/utils/__init__.py
claude_wrapper/utils/config.py
claude_wrapper/utils/streaming.py
claude_wrapper-0.1.dev15.dist-info/METADATA
claude_wrapper-0.1.dev15.dist-info/WHEEL
claude_wrapper-0.1.dev15.dist-info/entry_points.txt
claude_wrapper-0.1.dev15.dist-info/licenses/LICENSE
claude_wrapper-0.1.dev15.dist-info/RECORD
