Metadata-Version: 2.4
Name: claude-wrapper
Version: 0.1.dev15
Summary: A simple Python wrapper for Claude CLI with streaming support and OpenAI-compatible API interface
Project-URL: Homepage, https://github.com/claude-wrapper/claude-wrapper
Project-URL: Documentation, https://github.com/claude-wrapper/claude-wrapper#readme
Project-URL: Repository, https://github.com/claude-wrapper/claude-wrapper
Project-URL: Issues, https://github.com/claude-wrapper/claude-wrapper/issues
Author: Claude Wrapper Contributors
License: MIT
License-File: LICENSE
Keywords: ai,api,claude,cli,fastapi,openai,streaming,typer
Classifier: Development Status :: 4 - Beta
Classifier: Environment :: Console
Classifier: Framework :: FastAPI
Classifier: Intended Audience :: Developers
Classifier: License :: OSI Approved :: MIT License
Classifier: Operating System :: OS Independent
Classifier: Programming Language :: Python :: 3
Classifier: Programming Language :: Python :: 3.10
Classifier: Programming Language :: Python :: 3.11
Classifier: Programming Language :: Python :: 3.12
Classifier: Topic :: Scientific/Engineering :: Artificial Intelligence
Classifier: Topic :: Software Development :: Libraries :: Python Modules
Requires-Python: >=3.10
Requires-Dist: aiofiles>=23.2.1
Requires-Dist: fastapi>=0.110.0
Requires-Dist: httpx>=0.25.0
Requires-Dist: orjson>=3.9.10
Requires-Dist: pydantic-settings>=2.1.0
Requires-Dist: pydantic>=2.5.0
Requires-Dist: python-dotenv>=1.0.0
Requires-Dist: python-multipart>=0.0.6
Requires-Dist: pyyaml>=6.0.0
Requires-Dist: rich>=13.7.0
Requires-Dist: sse-starlette>=2.0.0
Requires-Dist: typer>=0.9.0
Requires-Dist: uvicorn[standard]>=0.27.0
Provides-Extra: dev
Requires-Dist: bandit>=1.7.0; extra == 'dev'
Requires-Dist: black>=23.0.0; extra == 'dev'
Requires-Dist: faker>=20.0.0; extra == 'dev'
Requires-Dist: freezegun>=1.2.0; extra == 'dev'
Requires-Dist: mypy>=1.7.0; extra == 'dev'
Requires-Dist: openai>=1.99.9; extra == 'dev'
Requires-Dist: pip-audit>=2.6.0; extra == 'dev'
Requires-Dist: pre-commit>=3.5.0; extra == 'dev'
Requires-Dist: pytest-asyncio>=0.21.0; extra == 'dev'
Requires-Dist: pytest-cov>=4.1.0; extra == 'dev'
Requires-Dist: pytest-mock>=3.11.0; extra == 'dev'
Requires-Dist: pytest-timeout>=2.1.0; extra == 'dev'
Requires-Dist: pytest>=7.4.0; extra == 'dev'
Requires-Dist: respx>=0.20.0; extra == 'dev'
Requires-Dist: ruff>=0.1.0; extra == 'dev'
Requires-Dist: tomli-w>=1.0.0; extra == 'dev'
Requires-Dist: types-pyyaml>=6.0.0; extra == 'dev'
Provides-Extra: test
Requires-Dist: faker>=20.0.0; extra == 'test'
Requires-Dist: freezegun>=1.2.0; extra == 'test'
Requires-Dist: openai>=1.99.9; extra == 'test'
Requires-Dist: pytest-asyncio>=0.21.0; extra == 'test'
Requires-Dist: pytest-cov>=4.1.0; extra == 'test'
Requires-Dist: pytest-mock>=3.11.0; extra == 'test'
Requires-Dist: pytest-timeout>=2.1.0; extra == 'test'
Requires-Dist: pytest>=7.4.0; extra == 'test'
Requires-Dist: respx>=0.20.0; extra == 'test'
